{
  "all_task_loss": 0.30857959141666663,
  "all_task_loss_available_count": 12,
  "all_task_loss_complete": true,
  "controller_diagnostics": {
    "note": "engineering diagnostic only; excluded from simulated time and core_digest",
    "sample_count": 22,
    "wall_clock_max_s": 0.0081071,
    "wall_clock_mean_s": 0.005319113636363637,
    "wall_clock_p50_s": 0.0053691,
    "wall_clock_p95_s": 0.00758582,
    "wall_clock_total_s": 0.1170205
  },
  "cost_latency_s": {
    "count": 12,
    "max": 1.220200956,
    "mean": 0.24611313283333305,
    "min": 0.1026006819999985,
    "p50": 0.16752892228571348,
    "p95": 0.673721451628571,
    "p99": 1.110905055125715
  },
  "coverage": 0.9166666666666666,
  "done_count": 11,
  "energy_j": {
    "physical_system": {
      "rsu": 1267.8989417199996,
      "rsu_by_id": {
        "rsu-1": 710.2517215679998,
        "rsu-2": 557.6472201519998
      },
      "total": 1421.8385692159368,
      "vehicle": 153.9396274959371,
      "vehicle_by_id": {
        "veh-1": 84.30248446588564,
        "veh-2": 69.63714303005143
      }
    },
    "task_attributed": {
      "rsu": 0.0,
      "total": 14.52782245793708,
      "vehicle": 14.52782245793708
    }
  },
  "fail_count": 1,
  "failure_rate": 0.08333333333333333,
  "failure_reasons": {
    "PREP_FAILED": 1
  },
  "invariant_check_count": 184,
  "invariant_failure_count": 0,
  "latency_p50_s": 0.14069720928571378,
  "latency_p95_s": 0.22173042857142905,
  "latency_p99_s": 0.22562757142857193,
  "metric_semantics": {
    "all_task_loss": "DONE FER loss; FAIL uses frozen config.cost.failure_loss",
    "cost_latency_s": "DONE latency, otherwise the configured relative deadline",
    "energy": "task attribution is distinct from independent physical system energy",
    "terminal_latency_s": "terminal_time-arrival_time for every terminal task"
  },
  "nonterminal_count": 0,
  "resources": {
    "max_residual_work_s": 0.22,
    "max_utilization": 0.0979900798059949,
    "max_waiting_jobs": 0,
    "mean_utilization": 0.019413392462440955,
    "pool_count": 10,
    "pools": {
      "rsu/rsu-1/rsu-1:gpu": {
        "busy_server_seconds": 0.22000000000000064,
        "cancelled_job_count": 0,
        "completed_job_count": 1,
        "job_count": 1,
        "max_residual_work_s": 0.22,
        "max_running_observed": 1,
        "max_waiting_jobs": 0,
        "owner_id": "rsu-1",
        "owner_type": "rsu",
        "resource_id": "rsu-1:gpu",
        "resource_kind": "rsu_gpu",
        "server_count": 2,
        "service_s": {
          "count": 1,
          "max": 0.22000000000000064,
          "mean": 0.22000000000000064,
          "min": 0.22000000000000064,
          "p50": 0.22000000000000064,
          "p95": 0.22000000000000064,
          "p99": 0.22000000000000064
        },
        "utilization": 0.0114409249601585,
        "wait_s": {
          "count": 1,
          "max": 0.0,
          "mean": 0.0,
          "min": 0.0,
          "p50": 0.0,
          "p95": 0.0,
          "p99": 0.0
        }
      },
      "rsu/rsu-1/rsu-1:ingress": {
        "busy_server_seconds": 0.0,
        "cancelled_job_count": 0,
        "completed_job_count": 0,
        "job_count": 0,
        "max_residual_work_s": 0.0,
        "max_running_observed": 0,
        "max_waiting_jobs": 0,
        "owner_id": "rsu-1",
        "owner_type": "rsu",
        "resource_id": "rsu-1:ingress",
        "resource_kind": "rsu_ingress_cpu",
        "server_count": 1,
        "service_s": {
          "count": 0,
          "max": null,
          "mean": null,
          "min": null,
          "p50": null,
          "p95": null,
          "p99": null
        },
        "utilization": 0.0,
        "wait_s": {
          "count": 0,
          "max": null,
          "mean": null,
          "min": null,
          "p50": null,
          "p95": null,
          "p99": null
        }
      },
      "rsu/rsu-2/rsu-2:gpu": {
        "busy_server_seconds": 0.0,
        "cancelled_job_count": 0,
        "completed_job_count": 0,
        "job_count": 0,
        "max_residual_work_s": 0.0,
        "max_running_observed": 0,
        "max_waiting_jobs": 0,
        "owner_id": "rsu-2",
        "owner_type": "rsu",
        "resource_id": "rsu-2:gpu",
        "resource_kind": "rsu_gpu",
        "server_count": 1,
        "service_s": {
          "count": 0,
          "max": null,
          "mean": null,
          "min": null,
          "p50": null,
          "p95": null,
          "p99": null
        },
        "utilization": 0.0,
        "wait_s": {
          "count": 0,
          "max": null,
          "mean": null,
          "min": null,
          "p50": null,
          "p95": null,
          "p99": null
        }
      },
      "rsu/rsu-2/rsu-2:ingress": {
        "busy_server_seconds": 0.0,
        "cancelled_job_count": 0,
        "completed_job_count": 0,
        "job_count": 0,
        "max_residual_work_s": 0.0,
        "max_running_observed": 0,
        "max_waiting_jobs": 0,
        "owner_id": "rsu-2",
        "owner_type": "rsu",
        "resource_id": "rsu-2:ingress",
        "resource_kind": "rsu_ingress_cpu",
        "server_count": 1,
        "service_s": {
          "count": 0,
          "max": null,
          "mean": null,
          "min": null,
          "p50": null,
          "p95": null,
          "p99": null
        },
        "utilization": 0.0,
        "wait_s": {
          "count": 0,
          "max": null,
          "mean": null,
          "min": null,
          "p50": null,
          "p95": null,
          "p99": null
        }
      },
      "vehicle/veh-1/veh-1:accelerator": {
        "busy_server_seconds": 0.5955674954285696,
        "cancelled_job_count": 0,
        "completed_job_count": 20,
        "job_count": 20,
        "max_residual_work_s": 0.0374,
        "max_running_observed": 1,
        "max_waiting_jobs": 0,
        "owner_id": "veh-1",
        "owner_type": "vehicle",
        "resource_id": "veh-1:accelerator",
        "resource_kind": "accelerator",
        "server_count": 1,
        "service_s": {
          "count": 20,
          "max": 0.05342857142857138,
          "mean": 0.02977837477142848,
          "min": 0.01824974800000012,
          "p50": 0.02590085799999997,
          "p95": 0.039924579285713926,
          "p99": 0.05072777299999987
        },
        "utilization": 0.06194402749007077,
        "wait_s": {
          "count": 20,
          "max": 0.0,
          "mean": 0.0,
          "min": 0.0,
          "p50": 0.0,
          "p95": 0.0,
          "p99": 0.0
        }
      },
      "vehicle/veh-1/veh-1:cpu": {
        "busy_server_seconds": 0.06321428571428656,
        "cancelled_job_count": 0,
        "completed_job_count": 8,
        "job_count": 8,
        "max_residual_work_s": 0.0075,
        "max_running_observed": 1,
        "max_waiting_jobs": 0,
        "owner_id": "veh-1",
        "owner_type": "vehicle",
        "resource_id": "veh-1:cpu",
        "resource_kind": "cpu",
        "server_count": 1,
        "service_s": {
          "count": 8,
          "max": 0.01071428571428612,
          "mean": 0.00790178571428582,
          "min": 0.00749999999999984,
          "p50": 0.007500000000000118,
          "p95": 0.009589285714286076,
          "p99": 0.01048928571428611
        },
        "utilization": 0.00657481726606518,
        "wait_s": {
          "count": 8,
          "max": 0.0,
          "mean": 0.0,
          "min": 0.0,
          "p50": 0.0,
          "p95": 0.0,
          "p99": 0.0
        }
      },
      "vehicle/veh-1/veh-1:encoder": {
        "busy_server_seconds": 0.04660803142857062,
        "cancelled_job_count": 0,
        "completed_job_count": 6,
        "job_count": 6,
        "max_residual_work_s": 0.00733472,
        "max_running_observed": 1,
        "max_waiting_jobs": 0,
        "owner_id": "veh-1",
        "owner_type": "vehicle",
        "resource_id": "veh-1:encoder",
        "resource_kind": "encoder",
        "server_count": 1,
        "service_s": {
          "count": 6,
          "max": 0.010302771428571056,
          "mean": 0.007768005238095103,
          "min": 0.007211939999999473,
          "p50": 0.007273329999999856,
          "p95": 0.009560758571428296,
          "p99": 0.010154368857142505
        },
        "utilization": 0.004847627182863489,
        "wait_s": {
          "count": 6,
          "max": 0.0,
          "mean": 0.0,
          "min": 0.0,
          "p50": 0.0,
          "p95": 0.0,
          "p99": 0.0
        }
      },
      "vehicle/veh-2/veh-2:accelerator": {
        "busy_server_seconds": 0.9421361311428567,
        "cancelled_job_count": 0,
        "completed_job_count": 19,
        "job_count": 19,
        "max_residual_work_s": 0.0682,
        "max_running_observed": 1,
        "max_waiting_jobs": 0,
        "owner_id": "veh-2",
        "owner_type": "vehicle",
        "resource_id": "veh-2:accelerator",
        "resource_kind": "accelerator",
        "server_count": 1,
        "service_s": {
          "count": 19,
          "max": 0.09742857142857186,
          "mean": 0.04958611216541351,
          "min": 0.025086853999999548,
          "p50": 0.04258281900000016,
          "p95": 0.08945714285714325,
          "p99": 0.09583428571428615
        },
        "utilization": 0.0979900798059949,
        "wait_s": {
          "count": 19,
          "max": 0.0,
          "mean": 0.0,
          "min": 0.0,
          "p50": 0.0,
          "p95": 0.0,
          "p99": 0.0
        }
      },
      "vehicle/veh-2/veh-2:cpu": {
        "busy_server_seconds": 0.06642857142857261,
        "cancelled_job_count": 0,
        "completed_job_count": 8,
        "job_count": 8,
        "max_residual_work_s": 0.0075,
        "max_running_observed": 1,
        "max_waiting_jobs": 0,
        "owner_id": "veh-2",
        "owner_type": "vehicle",
        "resource_id": "veh-2:cpu",
        "resource_kind": "cpu",
        "server_count": 1,
        "service_s": {
          "count": 8,
          "max": 0.01071428571428612,
          "mean": 0.008303571428571577,
          "min": 0.00749999999999984,
          "p50": 0.007500000000000173,
          "p95": 0.01071428571428612,
          "p99": 0.01071428571428612
        },
        "utilization": 0.0069091300084075085,
        "wait_s": {
          "count": 8,
          "max": 0.0,
          "mean": 0.0,
          "min": 0.0,
          "p50": 0.0,
          "p95": 0.0,
          "p99": 0.0
        }
      },
      "vehicle/veh-2/veh-2:encoder": {
        "busy_server_seconds": 0.04256692285714192,
        "cancelled_job_count": 0,
        "completed_job_count": 5,
        "job_count": 5,
        "max_residual_work_s": 0.00733472,
        "max_running_observed": 1,
        "max_waiting_jobs": 0,
        "owner_id": "veh-2",
        "owner_type": "vehicle",
        "resource_id": "veh-2:encoder",
        "resource_kind": "encoder",
        "server_count": 1,
        "service_s": {
          "count": 5,
          "max": 0.010302771428571056,
          "mean": 0.008513384571428384,
          "min": 0.007291939999999997,
          "p50": 0.007334720000000017,
          "p95": 0.010302771428571056,
          "p99": 0.010302771428571056
        },
        "utilization": 0.004427317910849227,
        "wait_s": {
          "count": 5,
          "max": 0.0,
          "mean": 0.0,
          "min": 0.0,
          "p50": 0.0,
          "p95": 0.0,
          "p99": 0.0
        }
      }
    }
  },
  "selected_path_fer_classification": {
    "accuracy": 1.0,
    "balanced_accuracy": 1.0,
    "by_route": {
      "edge": {
        "accuracy": null,
        "balanced_accuracy": null,
        "expected_calibration_error": null,
        "macro_f1": null,
        "negative_log_likelihood": null,
        "per_class_recall": {},
        "sample_count": 0
      },
      "local": {
        "accuracy": 1.0,
        "balanced_accuracy": 1.0,
        "class_labels": [
          "angry",
          "happy",
          "neutral",
          "sad"
        ],
        "ece_bins": 10,
        "expected_calibration_error": 0.24572319037720106,
        "macro_f1": 1.0,
        "negative_log_likelihood": 0.28349425450737686,
        "per_class_recall": {
          "angry": 1.0,
          "happy": 1.0,
          "neutral": 1.0,
          "sad": 1.0
        },
        "sample_count": 11
      }
    },
    "class_labels": [
      "angry",
      "happy",
      "neutral",
      "sad"
    ],
    "ece_bins": 10,
    "expected_calibration_error": 0.24572319037720106,
    "macro_f1": 1.0,
    "missing_done_prediction_count": 0,
    "negative_log_likelihood": 0.28349425450737686,
    "per_class_recall": {
      "angry": 1.0,
      "happy": 1.0,
      "neutral": 1.0,
      "sad": 1.0
    },
    "sample_count": 11,
    "scope": "DONE tasks using the FER prediction on the actually selected path",
    "subject_cluster_report": {
      "cluster_count": 5,
      "macro_accuracy": 1.0,
      "task_level_identifiers_emitted": false,
      "unit": "subject_cluster"
    }
  },
  "success_conditional_fer_available_count": 11,
  "success_conditional_fer_loss": 0.2457231906363636,
  "success_conditional_fer_missing_count": 0,
  "successful_latency_s": {
    "count": 11,
    "max": 0.22660185714285763,
    "mean": 0.1575596943636361,
    "min": 0.1026006819999985,
    "p50": 0.14827139857142768,
    "p95": 0.22217328571428618,
    "p99": 0.22571614285714334
  },
  "task_count": 12,
  "terminal_latency_s": {
    "count": 12,
    "max": 0.22660185714285763,
    "mean": 0.14784345316666636,
    "min": 0.04096479999999936,
    "p50": 0.14069720928571378,
    "p95": 0.22173042857142905,
    "p99": 0.22562757142857193
  },
  "timeout_count": 0,
  "timeout_rate": 0.0,
  "virtual_queues_final": {
    "coverage": 0.75,
    "failure": 1.0,
    "rsu_power": {
      "rsu-1": 0.0,
      "rsu-2": 0.0
    },
    "timeout": 0.0,
    "vehicle_power": {
      "veh-1": 0.0,
      "veh-2": 0.0
    }
  }
}
